README.rst
setup.cfg
setup.py
sqlite4dummy/__init__.py
sqlite4dummy/dtype.py
sqlite4dummy/engine.py
sqlite4dummy/func.py
sqlite4dummy/iterate.py
sqlite4dummy/pycompatible.py
sqlite4dummy/row.py
sqlite4dummy/schema.py
sqlite4dummy/sql.py
sqlite4dummy/statement.py
sqlite4dummy/validate.py
sqlite4dummy/zzz_manual_install.py
sqlite4dummy.egg-info/PKG-INFO
sqlite4dummy.egg-info/SOURCES.txt
sqlite4dummy.egg-info/dependency_links.txt
sqlite4dummy.egg-info/top_level.txt
sqlite4dummy/tests/__init__.py
sqlite4dummy/tests/test_Column.py
sqlite4dummy/tests/test_Delete.py
sqlite4dummy/tests/test_Index.py
sqlite4dummy/tests/test_Insert.py
sqlite4dummy/tests/test_MetaData.py
sqlite4dummy/tests/test_Select.py
sqlite4dummy/tests/test_Table.py
sqlite4dummy/tests/test_Update.py
sqlite4dummy/tests/test_database_setting.py
sqlite4dummy/tests/test_func.py